Metadata-Version: 2.4
Name: pych-client-elena
Version: 0.4.1
Summary: A ClickHouse client for Python, with a command-line interface.
License: MIT
License-File: LICENSE
Author: Maxime Mouchet
Author-email: maxime.mouchet@lip6.fr
Requires-Python: >=3.8,<4.0
Classifier: License :: OSI Approved :: MIT License
Classifier: Programming Language :: Python :: 3
Classifier: Programming Language :: Python :: 3.8
Classifier: Programming Language :: Python :: 3.9
Classifier: Programming Language :: Python :: 3.10
Classifier: Programming Language :: Python :: 3.11
Classifier: Programming Language :: Python :: 3.12
Classifier: Programming Language :: Python :: 3.13
Classifier: Programming Language :: Python :: 3.14
Provides-Extra: orjson
Requires-Dist: httpx (>=0.25.0,<0.26.0)
Requires-Dist: orjson (>=3.9.10,<4.0.0) ; extra == "orjson"
Project-URL: Homepage, https://github.com/dioptra-io/pych-client
